{
    "name": "Forum",
    "base": "PersistedModel",
    "idInjection": false,
    "options": {
        "validateUpsert": true
    },
    "properties": {
        "_id": {
            "type": "String"
        },
        "question": {
            "type": "String",
            "default": ""
        },
        "description": {
            "type": "String",
            "default": ""
        },
        "presentDate": {
            "type": "Date"
        }
    },
    "validations": [],
    "relations": {
        "answers": {
            "type": "hasMany",
            "model": "ForumAnswers",
            "foreignKey": ""
        }
    },
    "acls": [],
    "methods": {}
}
